Smail.py
Smail-0.1.9.dist-info/LICENSE
Smail-0.1.9.dist-info/METADATA
Smail-0.1.9.dist-info/WHEEL
Smail-0.1.9.dist-info/top_level.txt
Smail-0.1.9.dist-info/RECORD
