Metadata-Version: 2.2
Name: Smail
Version: 0.1.9
Summary: Python send mail
Home-page: https://github.com/Aliencn/Smail
Author: Alien
Author-email: Aliencn@outlook.com
License: GPL
License-File: LICENSE
Dynamic: author
Dynamic: author-email
Dynamic: description
Dynamic: home-page
Dynamic: license
Dynamic: summary
